amaazetools/__init__.py
amaazetools/cextensions.cp39-win_amd64.pyd
amaazetools/dicom.py
amaazetools/edge_detection.py
amaazetools/mesh_segmentation.py
amaazetools/svi.py
amaazetools/trimesh.py
amaazetools-0.2.0.dist-info/licenses/LICENSE
amaazetools-0.2.0.dist-info/METADATA
amaazetools-0.2.0.dist-info/WHEEL
amaazetools-0.2.0.dist-info/top_level.txt
amaazetools-0.2.0.dist-info/RECORD
