Metadata-Version: 2.1
Name: amaazetools
Version: 0.2.0
Summary: Python package for mesh processing tools developed by AMAAZE
Author-email: Jeff Calder <jwcalder@umn.edu>
License: MIT
Project-URL: Homepage, https://github.com/jwcalder/AMAAZETools
Project-URL: Bug Tracker, https://github.com/jwcalder/AMAAZETools/issues
Classifier: Programming Language :: Python :: 3
Classifier: License :: OSI Approved :: MIT License
Classifier: Operating System :: OS Independent
Requires-Python: >=3.6
License-File: LICENSE
Requires-Dist: numpy
Requires-Dist: scipy
Requires-Dist: pandas
Requires-Dist: pydicom
Requires-Dist: scikit-image
Requires-Dist: scikit-learn
Requires-Dist: matplotlib
Requires-Dist: graphlearning
Requires-Dist: plyfile
